nanoid_dictionary/__init__.py
nanoid_dictionary-2.4.0.dist-info/LICENSE
nanoid_dictionary-2.4.0.dist-info/METADATA
nanoid_dictionary-2.4.0.dist-info/WHEEL
nanoid_dictionary-2.4.0.dist-info/top_level.txt
nanoid_dictionary-2.4.0.dist-info/RECORD
