Metadata-Version: 2.1
Name: nanoid-dictionary
Version: 2.4.0
Summary: Predefined character sets to be used with Nano ID
Home-page: https://github.com/aidarkhanov/py-nanoid-dictionary
Author: Dair Aidarkhanov
Author-email: dairaidarkhanov@gmail.com
License: MIT
Platform: UNKNOWN
Classifier: License :: OSI Approved :: MIT License
Classifier: Programming Language :: Python
Classifier: Operating System :: OS Independent
Classifier: Topic :: Utilities
